{"_ts":[1575160643,1575204444,1575248940],"_r":{"breakdown":{"html":{"bytes":[67574,100239,67671],"requests":[18,24,17]},"js":{"bytes":[1468756,2475655,1420685],"requests":[137,248,133]},"css":{"bytes":[114150,114150,114150],"requests":[6,6,6]},"image":{"bytes":[905556,905533,1854173],"requests":[46,46,58]},"flash":{"bytes":[0,0,0],"requests":[0,0,0]},"font":{"bytes":[103152,103152,103152],"requests":[5,5,5]},"video":{"bytes":[0,0,0],"requests":[0,0,0]},"other":{"bytes":[22563,22902,23086],"requests":[48,53,46]}},"date":[1575160643,1575204444,1575248940],"domElements":[1554,1555,1423],"domInteractive":[6491,6186,5988],"firstPaint":[6634.0199999977,6334.4849999994,6134.1949999987],"fullyLoaded":[33496,38389,35688],"id":["191201_EZ_d2f33c91356d9c6f5abf505195de6123","191201_XA_7c6d7f0c2094f10032e0bb7becc9ad40","191202_9H_a53658194ae35943b9f99e96af0fb4e2"],"loadTime":[24001,23794,27092],"render":[6700,6400,6200],"SpeedIndex":[9142,8832,8949],"TTFB":[5042,4667,4503],"videoFrames":[[{"_i":"ms_000000.jpg","_t":0,"_vc":0},{"_i":"ms_006700.jpg","_t":6700,"_vc":13},{"_i":"ms_007100.jpg","_t":7100,"_vc":12},{"_i":"ms_007200.jpg","_t":7200,"_vc":12},{"_i":"ms_007300.jpg","_t":7300,"_vc":12},{"_i":"ms_007500.jpg","_t":7500,"_vc":12},{"_i":"ms_008000.jpg","_t":8000,"_vc":93},{"_i":"ms_008500.jpg","_t":8500,"_vc":91},{"_i":"ms_009800.jpg","_t":9800,"_vc":92},{"_i":"ms_010300.jpg","_t":10300,"_vc":92},{"_i":"ms_010400.jpg","_t":10400,"_vc":91},{"_i":"ms_010500.jpg","_t":10500,"_vc":91},{"_i":"ms_012600.jpg","_t":12600,"_vc":91},{"_i":"ms_013100.jpg","_t":13100,"_vc":92},{"_i":"ms_013200.jpg","_t":13200,"_vc":91},{"_i":"ms_013300.jpg","_t":13300,"_vc":91},{"_i":"ms_013800.jpg","_t":13800,"_vc":91},{"_i":"ms_013900.jpg","_t":13900,"_vc":91},{"_i":"ms_014100.jpg","_t":14100,"_vc":92},{"_i":"ms_014900.jpg","_t":14900,"_vc":92},{"_i":"ms_015100.jpg","_t":15100,"_vc":92},{"_i":"ms_015300.jpg","_t":15300,"_vc":92},{"_i":"ms_015800.jpg","_t":15800,"_vc":92},{"_i":"ms_016400.jpg","_t":16400,"_vc":92},{"_i":"ms_016500.jpg","_t":16500,"_vc":91},{"_i":"ms_016800.jpg","_t":16800,"_vc":92},{"_i":"ms_017600.jpg","_t":17600,"_vc":92},{"_i":"ms_017800.jpg","_t":17800,"_vc":92},{"_i":"ms_018000.jpg","_t":18000,"_vc":92},{"_i":"ms_018100.jpg","_t":18100,"_vc":93},{"_i":"ms_018200.jpg","_t":18200,"_vc":91},{"_i":"ms_018300.jpg","_t":18300,"_vc":91},{"_i":"ms_018400.jpg","_t":18400,"_vc":91},{"_i":"ms_018600.jpg","_t":18600,"_vc":91},{"_i":"ms_022700.jpg","_t":22700,"_vc":91},{"_i":"ms_022800.jpg","_t":22800,"_vc":92},{"_i":"ms_022900.jpg","_t":22900,"_vc":94},{"_i":"ms_023000.jpg","_t":23000,"_vc":97},{"_i":"ms_023100.jpg","_t":23100,"_vc":97},{"_i":"ms_023200.jpg","_t":23200,"_vc":98},{"_i":"ms_023300.jpg","_t":23300,"_vc":98},{"_i":"ms_023400.jpg","_t":23400,"_vc":99},{"_i":"ms_023500.jpg","_t":23500,"_vc":99},{"_i":"ms_023600.jpg","_t":23600,"_vc":100}],[{"_i":"ms_000000.jpg","_t":0,"_vc":0},{"_i":"ms_006400.jpg","_t":6400,"_vc":13},{"_i":"ms_006600.jpg","_t":6600,"_vc":13},{"_i":"ms_006700.jpg","_t":6700,"_vc":14},{"_i":"ms_006800.jpg","_t":6800,"_vc":14},{"_i":"ms_006900.jpg","_t":6900,"_vc":14},{"_i":"ms_007000.jpg","_t":7000,"_vc":14},{"_i":"ms_007300.jpg","_t":7300,"_vc":13},{"_i":"ms_007700.jpg","_t":7700,"_vc":93},{"_i":"ms_008200.jpg","_t":8200,"_vc":91},{"_i":"ms_009000.jpg","_t":9000,"_vc":92},{"_i":"ms_009600.jpg","_t":9600,"_vc":92},{"_i":"ms_009700.jpg","_t":9700,"_vc":91},{"_i":"ms_009800.jpg","_t":9800,"_vc":91},{"_i":"ms_010300.jpg","_t":10300,"_vc":92},{"_i":"ms_010800.jpg","_t":10800,"_vc":92},{"_i":"ms_010900.jpg","_t":10900,"_vc":91},{"_i":"ms_011000.jpg","_t":11000,"_vc":92},{"_i":"ms_011600.jpg","_t":11600,"_vc":92},{"_i":"ms_011700.jpg","_t":11700,"_vc":91},{"_i":"ms_012300.jpg","_t":12300,"_vc":91},{"_i":"ms_012500.jpg","_t":12500,"_vc":92},{"_i":"ms_013300.jpg","_t":13300,"_vc":92},{"_i":"ms_013500.jpg","_t":13500,"_vc":91},{"_i":"ms_014700.jpg","_t":14700,"_vc":92},{"_i":"ms_015100.jpg","_t":15100,"_vc":92},{"_i":"ms_015501.jpg","_t":15501,"_vc":92},{"_i":"ms_016100.jpg","_t":16100,"_vc":92},{"_i":"ms_016600.jpg","_t":16600,"_vc":92},{"_i":"ms_017100.jpg","_t":17100,"_vc":92},{"_i":"ms_017500.jpg","_t":17500,"_vc":92},{"_i":"ms_018000.jpg","_t":18000,"_vc":91},{"_i":"ms_018900.jpg","_t":18900,"_vc":92},{"_i":"ms_019000.jpg","_t":19000,"_vc":91},{"_i":"ms_022500.jpg","_t":22500,"_vc":91},{"_i":"ms_023000.jpg","_t":23000,"_vc":99},{"_i":"ms_023400.jpg","_t":23400,"_vc":100}],[{"_i":"ms_000000.jpg","_t":0,"_vc":0},{"_i":"ms_006200.jpg","_t":6200,"_vc":13},{"_i":"ms_006500.jpg","_t":6500,"_vc":13},{"_i":"ms_006600.jpg","_t":6600,"_vc":13},{"_i":"ms_006700.jpg","_t":6700,"_vc":12},{"_i":"ms_006800.jpg","_t":6800,"_vc":12},{"_i":"ms_007500.jpg","_t":7500,"_vc":93},{"_i":"ms_008100.jpg","_t":8100,"_vc":91},{"_i":"ms_008300.jpg","_t":8300,"_vc":91},{"_i":"ms_009100.jpg","_t":9100,"_vc":92},{"_i":"ms_009200.jpg","_t":9200,"_vc":91},{"_i":"ms_009300.jpg","_t":9300,"_vc":91},{"_i":"ms_009600.jpg","_t":9600,"_vc":91},{"_i":"ms_010100.jpg","_t":10100,"_vc":92},{"_i":"ms_010200.jpg","_t":10200,"_vc":91},{"_i":"ms_010300.jpg","_t":10300,"_vc":91},{"_i":"ms_011300.jpg","_t":11300,"_vc":91},{"_i":"ms_011900.jpg","_t":11900,"_vc":92},{"_i":"ms_012000.jpg","_t":12000,"_vc":91},{"_i":"ms_012100.jpg","_t":12100,"_vc":91},{"_i":"ms_012600.jpg","_t":12600,"_vc":92},{"_i":"ms_013400.jpg","_t":13400,"_vc":92},{"_i":"ms_013500.jpg","_t":13500,"_vc":91},{"_i":"ms_014400.jpg","_t":14400,"_vc":91},{"_i":"ms_014800.jpg","_t":14800,"_vc":91},{"_i":"ms_015100.jpg","_t":15100,"_vc":91},{"_i":"ms_016200.jpg","_t":16200,"_vc":91},{"_i":"ms_016500.jpg","_t":16500,"_vc":91},{"_i":"ms_017200.jpg","_t":17200,"_vc":91},{"_i":"ms_017700.jpg","_t":17700,"_vc":91},{"_i":"ms_018100.jpg","_t":18100,"_vc":93},{"_i":"ms_027200.jpg","_t":27200,"_vc":91},{"_i":"ms_027500.jpg","_t":27500,"_vc":97},{"_i":"ms_028000.jpg","_t":28000,"_vc":99},{"_i":"ms_028100.jpg","_t":28100,"_vc":100}]],"visualComplete":[23600,23400,28100],"lighthouse":[38,38,38],"pagespeed":[null,88,88]}}