{"_ts":[1493618693,1493665770,1493795266],"_r":{"breakdown":{"html":{"bytes":[141988,141873,141867],"requests":[12,10,11]},"js":{"bytes":[1376087,1376388,1367014],"requests":[40,40,39]},"css":{"bytes":[75832,75832,75552],"requests":[4,4,4]},"image":{"bytes":[1233456,1630869,1415011],"requests":[52,55,53]},"flash":{"bytes":[0,0,0],"requests":[0,0,0]},"font":{"bytes":[173493,173493,173493],"requests":[3,3,3]},"other":{"bytes":[12237,13165,11548],"requests":[13,14,15]}},"date":[1493618693,1493665770,1493795266],"domElements":[2032,2013,2014],"domInteractive":[9828,8836,10072],"firstPaint":[9819,8832,10063],"fullyLoaded":[29975.258000195,34347.362000029,30279],"id":["170501_C1_B1Z","170501_8S_10V8","170503_RW_CB3"],"loadTime":[23399,26845,25023],"render":[9829,6601,10078],"SpeedIndex":[14996,12258,14016],"TTFB":[8283,6678,8451],"videoFrames":[[{"_i":"ms_000000.jpg","_t":0,"_vc":0},{"_i":"ms_009829.jpg","_t":9829,"_vc":22},{"_i":"ms_009852.jpg","_t":9852,"_vc":22},{"_i":"ms_009872.jpg","_t":9872,"_vc":22},{"_i":"ms_009886.jpg","_t":9886,"_vc":22},{"_i":"ms_009897.jpg","_t":9897,"_vc":22},{"_i":"ms_009914.jpg","_t":9914,"_vc":22},{"_i":"ms_009931.jpg","_t":9931,"_vc":22},{"_i":"ms_009947.jpg","_t":9947,"_vc":22},{"_i":"ms_009963.jpg","_t":9963,"_vc":22},{"_i":"ms_010014.jpg","_t":10014,"_vc":22},{"_i":"ms_010116.jpg","_t":10116,"_vc":22},{"_i":"ms_010213.jpg","_t":10213,"_vc":22},{"_i":"ms_010313.jpg","_t":10313,"_vc":22},{"_i":"ms_010414.jpg","_t":10414,"_vc":22},{"_i":"ms_010513.jpg","_t":10513,"_vc":22},{"_i":"ms_010613.jpg","_t":10613,"_vc":22},{"_i":"ms_010720.jpg","_t":10720,"_vc":22},{"_i":"ms_010805.jpg","_t":10805,"_vc":22},{"_i":"ms_010913.jpg","_t":10913,"_vc":22},{"_i":"ms_011014.jpg","_t":11014,"_vc":22},{"_i":"ms_011114.jpg","_t":11114,"_vc":22},{"_i":"ms_011213.jpg","_t":11213,"_vc":22},{"_i":"ms_011314.jpg","_t":11314,"_vc":22},{"_i":"ms_011414.jpg","_t":11414,"_vc":22},{"_i":"ms_011514.jpg","_t":11514,"_vc":22},{"_i":"ms_011614.jpg","_t":11614,"_vc":22},{"_i":"ms_011714.jpg","_t":11714,"_vc":22},{"_i":"ms_011814.jpg","_t":11814,"_vc":22},{"_i":"ms_011913.jpg","_t":11913,"_vc":22},{"_i":"ms_012014.jpg","_t":12014,"_vc":22},{"_i":"ms_012114.jpg","_t":12114,"_vc":31},{"_i":"ms_012214.jpg","_t":12214,"_vc":31},{"_i":"ms_012314.jpg","_t":12314,"_vc":31},{"_i":"ms_012439.jpg","_t":12439,"_vc":31},{"_i":"ms_012514.jpg","_t":12514,"_vc":37},{"_i":"ms_012614.jpg","_t":12614,"_vc":37},{"_i":"ms_012716.jpg","_t":12716,"_vc":37},{"_i":"ms_012814.jpg","_t":12814,"_vc":37},{"_i":"ms_012913.jpg","_t":12913,"_vc":37},{"_i":"ms_013014.jpg","_t":13014,"_vc":37},{"_i":"ms_013113.jpg","_t":13113,"_vc":37},{"_i":"ms_013205.jpg","_t":13205,"_vc":37},{"_i":"ms_013315.jpg","_t":13315,"_vc":37},{"_i":"ms_013408.jpg","_t":13408,"_vc":37},{"_i":"ms_013501.jpg","_t":13501,"_vc":37},{"_i":"ms_013637.jpg","_t":13637,"_vc":37},{"_i":"ms_013709.jpg","_t":13709,"_vc":37},{"_i":"ms_013814.jpg","_t":13814,"_vc":37},{"_i":"ms_013914.jpg","_t":13914,"_vc":37},{"_i":"ms_014001.jpg","_t":14001,"_vc":37},{"_i":"ms_014100.jpg","_t":14100,"_vc":37},{"_i":"ms_014212.jpg","_t":14212,"_vc":37},{"_i":"ms_014322.jpg","_t":14322,"_vc":37},{"_i":"ms_014414.jpg","_t":14414,"_vc":38},{"_i":"ms_014514.jpg","_t":14514,"_vc":38},{"_i":"ms_014614.jpg","_t":14614,"_vc":38},{"_i":"ms_014700.jpg","_t":14700,"_vc":38},{"_i":"ms_014814.jpg","_t":14814,"_vc":38},{"_i":"ms_015003.jpg","_t":15003,"_vc":38},{"_i":"ms_015520.jpg","_t":15520,"_vc":38},{"_i":"ms_016004.jpg","_t":16004,"_vc":99},{"_i":"ms_016514.jpg","_t":16514,"_vc":34},{"_i":"ms_017014.jpg","_t":17014,"_vc":35},{"_i":"ms_017504.jpg","_t":17504,"_vc":36},{"_i":"ms_017930.jpg","_t":17930,"_vc":100}],[{"_i":"ms_000000.jpg","_t":0,"_vc":0},{"_i":"ms_006601.jpg","_t":6601,"_vc":31},{"_i":"ms_006616.jpg","_t":6616,"_vc":31},{"_i":"ms_006644.jpg","_t":6644,"_vc":31},{"_i":"ms_006661.jpg","_t":6661,"_vc":31},{"_i":"ms_006678.jpg","_t":6678,"_vc":31},{"_i":"ms_006695.jpg","_t":6695,"_vc":31},{"_i":"ms_006711.jpg","_t":6711,"_vc":31},{"_i":"ms_006727.jpg","_t":6727,"_vc":31},{"_i":"ms_006744.jpg","_t":6744,"_vc":31},{"_i":"ms_006811.jpg","_t":6811,"_vc":31},{"_i":"ms_006903.jpg","_t":6903,"_vc":31},{"_i":"ms_007011.jpg","_t":7011,"_vc":37},{"_i":"ms_007111.jpg","_t":7111,"_vc":37},{"_i":"ms_007211.jpg","_t":7211,"_vc":37},{"_i":"ms_007310.jpg","_t":7310,"_vc":37},{"_i":"ms_007410.jpg","_t":7410,"_vc":37},{"_i":"ms_007516.jpg","_t":7516,"_vc":37},{"_i":"ms_007610.jpg","_t":7610,"_vc":37},{"_i":"ms_007710.jpg","_t":7710,"_vc":37},{"_i":"ms_007810.jpg","_t":7810,"_vc":37},{"_i":"ms_007911.jpg","_t":7911,"_vc":37},{"_i":"ms_008023.jpg","_t":8023,"_vc":37},{"_i":"ms_008111.jpg","_t":8111,"_vc":37},{"_i":"ms_008211.jpg","_t":8211,"_vc":37},{"_i":"ms_008311.jpg","_t":8311,"_vc":37},{"_i":"ms_008411.jpg","_t":8411,"_vc":37},{"_i":"ms_008515.jpg","_t":8515,"_vc":37},{"_i":"ms_008610.jpg","_t":8610,"_vc":37},{"_i":"ms_008711.jpg","_t":8711,"_vc":37},{"_i":"ms_008810.jpg","_t":8810,"_vc":37},{"_i":"ms_008917.jpg","_t":8917,"_vc":37},{"_i":"ms_009010.jpg","_t":9010,"_vc":37},{"_i":"ms_009110.jpg","_t":9110,"_vc":37},{"_i":"ms_009210.jpg","_t":9210,"_vc":37},{"_i":"ms_009311.jpg","_t":9311,"_vc":37},{"_i":"ms_009410.jpg","_t":9410,"_vc":37},{"_i":"ms_009510.jpg","_t":9510,"_vc":37},{"_i":"ms_009610.jpg","_t":9610,"_vc":37},{"_i":"ms_009711.jpg","_t":9711,"_vc":37},{"_i":"ms_009810.jpg","_t":9810,"_vc":37},{"_i":"ms_009910.jpg","_t":9910,"_vc":37},{"_i":"ms_010011.jpg","_t":10011,"_vc":37},{"_i":"ms_010110.jpg","_t":10110,"_vc":37},{"_i":"ms_010210.jpg","_t":10210,"_vc":37},{"_i":"ms_010310.jpg","_t":10310,"_vc":37},{"_i":"ms_010411.jpg","_t":10411,"_vc":37},{"_i":"ms_010511.jpg","_t":10511,"_vc":37},{"_i":"ms_010611.jpg","_t":10611,"_vc":37},{"_i":"ms_011524.jpg","_t":11524,"_vc":37},{"_i":"ms_012011.jpg","_t":12011,"_vc":37},{"_i":"ms_012511.jpg","_t":12511,"_vc":37},{"_i":"ms_013008.jpg","_t":13008,"_vc":37},{"_i":"ms_013500.jpg","_t":13500,"_vc":37},{"_i":"ms_014054.jpg","_t":14054,"_vc":37},{"_i":"ms_014505.jpg","_t":14505,"_vc":37},{"_i":"ms_015027.jpg","_t":15027,"_vc":33},{"_i":"ms_015510.jpg","_t":15510,"_vc":99},{"_i":"ms_015577.jpg","_t":15577,"_vc":100}],[{"_i":"ms_000000.jpg","_t":0,"_vc":0},{"_i":"ms_010078.jpg","_t":10078,"_vc":34},{"_i":"ms_010182.jpg","_t":10182,"_vc":34},{"_i":"ms_010298.jpg","_t":10298,"_vc":34},{"_i":"ms_010413.jpg","_t":10413,"_vc":34},{"_i":"ms_010513.jpg","_t":10513,"_vc":33},{"_i":"ms_010629.jpg","_t":10629,"_vc":33},{"_i":"ms_010729.jpg","_t":10729,"_vc":33},{"_i":"ms_010830.jpg","_t":10830,"_vc":33},{"_i":"ms_010946.jpg","_t":10946,"_vc":34},{"_i":"ms_011049.jpg","_t":11049,"_vc":36},{"_i":"ms_011163.jpg","_t":11163,"_vc":36},{"_i":"ms_011263.jpg","_t":11263,"_vc":36},{"_i":"ms_011379.jpg","_t":11379,"_vc":35},{"_i":"ms_011480.jpg","_t":11480,"_vc":35},{"_i":"ms_011596.jpg","_t":11596,"_vc":36},{"_i":"ms_011696.jpg","_t":11696,"_vc":36},{"_i":"ms_011797.jpg","_t":11797,"_vc":36},{"_i":"ms_011897.jpg","_t":11897,"_vc":36},{"_i":"ms_012013.jpg","_t":12013,"_vc":36},{"_i":"ms_012129.jpg","_t":12129,"_vc":35},{"_i":"ms_012271.jpg","_t":12271,"_vc":35},{"_i":"ms_012379.jpg","_t":12379,"_vc":52},{"_i":"ms_012501.jpg","_t":12501,"_vc":52},{"_i":"ms_012613.jpg","_t":12613,"_vc":52},{"_i":"ms_012713.jpg","_t":12713,"_vc":52},{"_i":"ms_012813.jpg","_t":12813,"_vc":52},{"_i":"ms_012913.jpg","_t":12913,"_vc":52},{"_i":"ms_013013.jpg","_t":13013,"_vc":52},{"_i":"ms_013129.jpg","_t":13129,"_vc":52},{"_i":"ms_013250.jpg","_t":13250,"_vc":52},{"_i":"ms_013351.jpg","_t":13351,"_vc":52},{"_i":"ms_013468.jpg","_t":13468,"_vc":52},{"_i":"ms_013586.jpg","_t":13586,"_vc":52},{"_i":"ms_013725.jpg","_t":13725,"_vc":52},{"_i":"ms_013830.jpg","_t":13830,"_vc":52},{"_i":"ms_013937.jpg","_t":13937,"_vc":52},{"_i":"ms_014062.jpg","_t":14062,"_vc":52},{"_i":"ms_014210.jpg","_t":14210,"_vc":52},{"_i":"ms_014327.jpg","_t":14327,"_vc":52},{"_i":"ms_014430.jpg","_t":14430,"_vc":50},{"_i":"ms_014551.jpg","_t":14551,"_vc":51},{"_i":"ms_014717.jpg","_t":14717,"_vc":50},{"_i":"ms_014830.jpg","_t":14830,"_vc":51},{"_i":"ms_014932.jpg","_t":14932,"_vc":52},{"_i":"ms_015048.jpg","_t":15048,"_vc":52},{"_i":"ms_015694.jpg","_t":15694,"_vc":51},{"_i":"ms_016029.jpg","_t":16029,"_vc":54},{"_i":"ms_016646.jpg","_t":16646,"_vc":52},{"_i":"ms_017001.jpg","_t":17001,"_vc":99},{"_i":"ms_017646.jpg","_t":17646,"_vc":51},{"_i":"ms_018082.jpg","_t":18082,"_vc":99},{"_i":"ms_018162.jpg","_t":18162,"_vc":100}]],"visualComplete":[17930,15577,18162],"lighthouse":[null,null,null],"pagespeed":[75,80,77]}}